yet_another_django_profiler/__init__.py
yet_another_django_profiler/conf.py
yet_another_django_profiler/middleware.py
yet_another_django_profiler/utils.py
yet_another_django_profiler/yadp_yappi.py
yet_another_django_profiler/locale/en/LC_MESSAGES/django.mo
yet_another_django_profiler/locale/ja/LC_MESSAGES/django.mo
yet_another_django_profiler/management/__init__.py
yet_another_django_profiler/management/commands/__init__.py
yet_another_django_profiler/management/commands/profile.py
yet_another_django_profiler-1.1.0.data/scripts/gprof2dot.py
yet_another_django_profiler-1.1.0.dist-info/DESCRIPTION.rst
yet_another_django_profiler-1.1.0.dist-info/METADATA
yet_another_django_profiler-1.1.0.dist-info/RECORD
yet_another_django_profiler-1.1.0.dist-info/WHEEL
yet_another_django_profiler-1.1.0.dist-info/metadata.json
yet_another_django_profiler-1.1.0.dist-info/top_level.txt
yet_another_django_profiler-1.1.0.dist-info/zip-safe
